popol/__init__.py
popol/__main__.py
popol/cache/__init__.py
popol/cache/backends/__init__.py
popol/cache/backends/base.py
popol/cache/backends/dummy.py
popol/cache/backends/redis.py
popol/cache/decorators.py
popol/cache/globals.py
popol/cache/helpers.py
popol/cache/key.py
popol/cache/serializers/__init__.py
popol/cache/serializers/base.py
popol/cache/serializers/json.py
popol/cache/serializers/pickle.py
popol/context/__init__.py
popol/context/globals.py
popol/context/proxy.py
popol/context/vars.py
popol/dantic.py
popol/db/__init__.py
popol/db/sqlmodel/__init__.py
popol/db/sqlmodel/globals.py
popol/db/sqlmodel/models.py
popol/email/__init__.py
popol/email/backend.py
popol/email/globals.py
popol/email/message.py
popol/jobs/__init__.py
popol/jobs/saq/__init__.py
popol/jobs/saq/cli.py
popol/jobs/saq/config.py
popol/jobs/saq/globals.py
popol/jobs/saq/queue.py
popol/json.py
popol/pagination.py
popol/schema.py
popol/templates/.pre-commit-config.yaml
popol/templates/README.md
popol/templates/app/__init__.py
popol/templates/app/extensions/__init__.py
popol/templates/app/main.py
popol/templates/app/middleware/__init__.py
popol/templates/app/routers/__init__.py
popol/templates/app/settings.py
popol/templates/pyproject.toml
popol/templates/requirements-dev.txt
popol/templates/requirements.txt
popol/templates/tests/__init__.py
popol/templates/tests/conftest.py
popol/utils.py
popol-0.6.0.dist-info/LICENSE
popol-0.6.0.dist-info/METADATA
popol-0.6.0.dist-info/WHEEL
popol-0.6.0.dist-info/entry_points.txt
popol-0.6.0.dist-info/RECORD
